image_merge.py
imagemerge-0.0.1.dist-info/METADATA
imagemerge-0.0.1.dist-info/WHEEL
imagemerge-0.0.1.dist-info/entry_points.txt
imagemerge-0.0.1.dist-info/top_level.txt
imagemerge-0.0.1.dist-info/RECORD
